flask_danger.py
Flask_Danger-1.0.9.dist-info/LICENSE
Flask_Danger-1.0.9.dist-info/METADATA
Flask_Danger-1.0.9.dist-info/WHEEL
Flask_Danger-1.0.9.dist-info/top_level.txt
Flask_Danger-1.0.9.dist-info/RECORD
