Metadata-Version: 2.1
Name: Flask-Danger
Version: 1.0.9
Summary: Flask extension for Danger (https://usedanger.com). Provides helpers to render the Danger widget on auth forms and to send server-side events.
Author-email: Danger <support@usedanger.com>
License: MIT License
Project-URL: Homepage, https://github.com/danger-org/flask-danger
Keywords: security,auth,timezone,country,geolocation,validation,risk,signup,login
Classifier: Environment :: Web Environment
Classifier: Intended Audience :: Developers
Classifier: License :: OSI Approved :: MIT License
Classifier: Operating System :: OS Independent
Classifier: Programming Language :: Python
Classifier: Programming Language :: Python :: 3
Classifier: Topic :: Internet :: WWW/HTTP :: Dynamic Content
Classifier: Topic :: Software Development :: Libraries :: Python Modules
License-File: LICENSE
Requires-Dist: flask
Requires-Dist: requests
Requires-Dist: markupsafe
